typename/__init__.py
typename-1.0.4.dist-info/LICENSE.txt
typename-1.0.4.dist-info/METADATA
typename-1.0.4.dist-info/WHEEL
typename-1.0.4.dist-info/top_level.txt
typename-1.0.4.dist-info/zip-safe
typename-1.0.4.dist-info/RECORD
