Metadata-Version: 2.1
Name: typename
Version: 1.0.4
Summary: Obtain the name of the type of an object
Home-page: https://github.com/sixty-north/typename
Author: Sixty North
Author-email: systems+typename@sixty-north.com
License: MIT License
Keywords: Python types typename
Classifier: Development Status :: 5 - Production/Stable
Classifier: Intended Audience :: Developers
Classifier: Topic :: Software Development :: Libraries :: Python Modules
Classifier: License :: OSI Approved :: MIT License
Classifier: Programming Language :: Python :: 3 :: Only
License-File: LICENSE.txt
Provides-Extra: dev
Requires-Dist: bumpversion ; extra == 'dev'
Requires-Dist: build ; extra == 'dev'
Requires-Dist: twine ; extra == 'dev'
Provides-Extra: test
Requires-Dist: pytest ; extra == 'test'
